[
    {
        "id": "1",
        "employeeId": "EMP001",
        "fullName": "John Doe",
        "dob": "1990-01-15",
        "gender": "male",
        "email": "john@company.com",
        "phone": "+91 9876543210",
        "street": "123 Main St",
        "city": "Mumbai",
        "state": "Maharashtra",
        "pincode": "400001",
        "emergencyContactName": "Jane Doe",
        "emergencyContactRelationship": "Spouse",
        "emergencyContactPhone": "+91 9876543211",
        "department": "Engineering",
        "designation": "Senior Software Engineer",
        "reportingManager": "Sarah Wilson",
        "dateOfJoining": "2020-06-01",
        "employmentType": "permanent",
        "accountNumber": "1234567890",
        "bankName": "HDFC Bank",
        "ifscCode": "HDFC0001234",
        "pan": "ABCDE1234F",
        "aadhaar": "123456789012",
        "uan": "123456789012",
        "esiNumber": "ESI123456",
        "basicSalary": 80000,
        "hra": 32000,
        "allowances": 15000,
        "deductions": 8000,
        "documents": "PAN Card, Aadhaar Card, Degree Certificate",
        "assets": "Laptop - Dell XPS 13, Monitor - Dell 27"
    },
    {
        "id": "2",
        "employeeId": "EMP002",
        "fullName": "Priya Sharma",
        "dob": "1992-08-22",
        "gender": "female",
        "email": "priya.sharma@company.com",
        "phone": "+91 9876543212",
        "street": "456 Park Avenue",
        "city": "Bangalore",
        "state": "Karnataka",
        "pincode": "560001",
        "emergencyContactName": "Rajesh Sharma",
        "emergencyContactRelationship": "Father",
        "emergencyContactPhone": "+91 9876543213",
        "department": "Product Management",
        "designation": "Product Manager",
        "reportingManager": "Michael Chen",
        "dateOfJoining": "2019-03-15",
        "employmentType": "permanent",
        "accountNumber": "2345678901",
        "bankName": "ICICI Bank",
        "ifscCode": "ICIC0002345",
        "pan": "FGHIJ5678K",
        "aadhaar": "234567890123",
        "uan": "234567890123",
        "esiNumber": "ESI234567",
        "basicSalary": 95000,
        "hra": 38000,
        "allowances": 20000,
        "deductions": 12000,
        "documents": "PAN Card, Aadhaar Card, MBA Certificate",
        "assets": "Laptop - MacBook Pro, iPad Air"
    },
    {
        "id": "3",
        "employeeId": "EMP003",
        "fullName": "Rahul Kumar",
        "dob": "1988-12-10",
        "gender": "male",
        "email": "rahul.kumar@company.com",
        "phone": "+91 9876543214",
        "street": "789 Tech Park Road",
        "city": "Hyderabad",
        "state": "Telangana",
        "pincode": "500081",
        "emergencyContactName": "Sunita Kumar",
        "emergencyContactRelationship": "Spouse",
        "emergencyContactPhone": "+91 9876543215",
        "department": "Quality Assurance",
        "designation": "QA Lead",
        "reportingManager": "David Brown",
        "dateOfJoining": "2021-01-10",
        "employmentType": "permanent",
        "accountNumber": "3456789012",
        "bankName": "Axis Bank",
        "ifscCode": "UTIB0003456",
        "pan": "KLMNO9012P",
        "aadhaar": "345678901234",
        "uan": "345678901234",
        "esiNumber": "ESI345678",
        "basicSalary": 70000,
        "hra": 28000,
        "allowances": 12000,
        "deductions": 6000,
        "documents": "PAN Card, Aadhaar Card, Experience Letters",
        "assets": "Laptop - Lenovo ThinkPad, Testing Device Kit"
    },
    {
        "id": "4",
        "employeeId": "EMP004",
        "fullName": "Ananya Patel",
        "dob": "1995-05-30",
        "gender": "female",
        "email": "ananya.patel@company.com",
        "phone": "+91 9876543216",
        "street": "321 Garden Street",
        "city": "Pune",
        "state": "Maharashtra",
        "pincode": "411001",
        "emergencyContactName": "Vikram Patel",
        "emergencyContactRelationship": "Brother",
        "emergencyContactPhone": "+91 9876543217",
        "department": "Design",
        "designation": "UI/UX Designer",
        "reportingManager": "Emily Roberts",
        "dateOfJoining": "2022-08-22",
        "employmentType": "contract",
        "accountNumber": "4567890123",
        "bankName": "SBI",
        "ifscCode": "SBIN0004567",
        "pan": "PQRST3456U",
        "aadhaar": "456789012345",
        "uan": "456789012345",
        "esiNumber": "ESI456789",
        "basicSalary": 60000,
        "hra": 24000,
        "allowances": 10000,
        "deductions": 5000,
        "documents": "PAN Card, Aadhaar Card, Design Portfolio",
        "assets": "Laptop - MacBook Air, Wacom Tablet"
    },
    {
        "id": "5",
        "employeeId": "EMP005",
        "fullName": "Amit Singh",
        "dob": "1991-11-18",
        "gender": "male",
        "email": "amit.singh@company.com",
        "phone": "+91 9876543218",
        "street": "654 Corporate Road",
        "city": "Gurgaon",
        "state": "Haryana",
        "pincode": "122001",
        "emergencyContactName": "Neha Singh",
        "emergencyContactRelationship": "Spouse",
        "emergencyContactPhone": "+91 9876543219",
        "department": "Sales",
        "designation": "Sales Manager",
        "reportingManager": "Robert Taylor",
        "dateOfJoining": "2018-11-05",
        "employmentType": "permanent",
        "accountNumber": "5678901234",
        "bankName": "Kotak Mahindra Bank",
        "ifscCode": "KKBK0005678",
        "pan": "UVWXY6789V",
        "aadhaar": "567890123456",
        "uan": "567890123456",
        "esiNumber": "ESI567890",
        "basicSalary": 85000,
        "hra": 34000,
        "allowances": 25000,
        "deductions": 15000,
        "documents": "PAN Card, Aadhaar Card, Sales Certifications",
        "assets": "Laptop - HP EliteBook, Company Car - Hyundai Creta"
    },
    {
        "id": "6",
        "employeeId": "EMP006",
        "fullName": "Sneha Reddy",
        "dob": "1993-03-25",
        "gender": "female",
        "email": "sneha.reddy@company.com",
        "phone": "+91 9876543220",
        "street": "987 Hills Road",
        "city": "Chennai",
        "state": "Tamil Nadu",
        "pincode": "600001",
        "emergencyContactName": "Arjun Reddy",
        "emergencyContactRelationship": "Husband",
        "emergencyContactPhone": "+91 9876543221",
        "department": "HR",
        "designation": "HR Business Partner",
        "reportingManager": "Lisa Wang",
        "dateOfJoining": "2020-02-14",
        "employmentType": "permanent",
        "accountNumber": "6789012345",
        "bankName": "Yes Bank",
        "ifscCode": "YESB0006789",
        "pan": "ZABCD1234W",
        "aadhaar": "678901234567",
        "uan": "678901234567",
        "esiNumber": "ESI678901",
        "basicSalary": 75000,
        "hra": 30000,
        "allowances": 15000,
        "deductions": 8000,
        "documents": "PAN Card, Aadhaar Card, HR Certifications",
        "assets": "Laptop - Dell Latitude, HR Software Access"
    },
    {
        "id": "7",
        "employeeId": "EMP007",
        "fullName": "Vikram Joshi",
        "dob": "1989-07-12",
        "gender": "male",
        "email": "vikram.joshi@company.com",
        "phone": "+91 9876543222",
        "street": "147 Lake View",
        "city": "Ahmedabad",
        "state": "Gujarat",
        "pincode": "380001",
        "emergencyContactName": "Meera Joshi",
        "emergencyContactRelationship": "Wife",
        "emergencyContactPhone": "+91 9876543223",
        "department": "Operations",
        "designation": "Operations Manager",
        "reportingManager": "Kevin Martinez",
        "dateOfJoining": "2017-09-08",
        "employmentType": "permanent",
        "accountNumber": "7890123456",
        "bankName": "Bank of Baroda",
        "ifscCode": "BARB0007890",
        "pan": "EFGHI2345X",
        "aadhaar": "789012345678",
        "uan": "789012345678",
        "esiNumber": "ESI789012",
        "basicSalary": 90000,
        "hra": 36000,
        "allowances": 18000,
        "deductions": 10000,
        "documents": "PAN Card, Aadhaar Card, Operations Certifications",
        "assets": "Laptop - Asus ZenBook, Operations Dashboard Access"
    }
]